django_mssql2/__init__.py
django_mssql2/base.py
django_mssql2/pyodbc/__init__.py
django_mssql2/pyodbc/base.py
django_mssql2/pyodbc/client.py
django_mssql2/pyodbc/compiler.py
django_mssql2/pyodbc/creation.py
django_mssql2/pyodbc/features.py
django_mssql2/pyodbc/introspection.py
django_mssql2/pyodbc/operations.py
django_mssql2/pyodbc/schema.py
django_mssql2-0.1.2.dist-info/WHEEL
django_mssql2-0.1.2.dist-info/METADATA
django_mssql2-0.1.2.dist-info/RECORD
