Metadata-Version: 2.1
Name: django-mssql2
Version: 0.1.2
Summary: Django database adapter for MS SQL Server
Author: Тряпчев Данил Павлович
Author-email: tryapchev@tochka.com
Requires-Python: >=3.6,<4.0
Classifier: Programming Language :: Python :: 3
Classifier: Programming Language :: Python :: 3.6
Classifier: Programming Language :: Python :: 3.7
Requires-Dist: Cython (>=0.29.13,<0.30.0)
Requires-Dist: django (>=2.2,<3.0)
Requires-Dist: pymssql (>=2.1,<3.0)
Requires-Dist: pyodbc (>=4.0,<5.0)
